kindlenotes2md/__init__.py
kindlenotes2md/dataclasses.py
kindlenotes2md/htmlparsing.py
kindlenotes2md/markdownoutput.py
kindlenotes2md/notes.py
kindlenotes2md-0.1.2.dist-info/entry_points.txt
kindlenotes2md-0.1.2.dist-info/WHEEL
kindlenotes2md-0.1.2.dist-info/METADATA
kindlenotes2md-0.1.2.dist-info/RECORD
