Metadata-Version: 2.1
Name: kindlenotes2md
Version: 0.1.2
Summary: Convert your kindle notes to markdown format
Home-page: https://github.com/dataewan/kindlenotes2md
Author: Ewan Nicolson
Author-email: ewan.nicolson@gmail.com
Requires-Python: >=3.8,<4.0
Classifier: Programming Language :: Python :: 3
Classifier: Programming Language :: Python :: 3.8
Classifier: Programming Language :: Python :: 3.9
Requires-Dist: click (>=7.1.2,<8.0.0)
Requires-Dist: pyquery (>=1.4.3,<2.0.0)
Project-URL: Repository, https://github.com/dataewan/kindlenotes2md
